{
  "version": "5",
  "dialect": "mysql",
  "id": "e883c381-8013-47cc-a831-f3f25c62b5b3",
  "prevId": "d020300d-2b8d-4e40-87dc-7980d3dde2df",
  "tables": {
    "pdfs": {
      "name": "pdfs",
      "columns": {
        "id": {
          "name": "id",
          "type": "serial",
          "primaryKey": false,
          "notNull": true,
          "autoincrement": true
        },
        "name": {
          "name": "name",
          "type": "varchar(40)",
          "primaryKey": false,
          "notNull": false,
          "autoincrement": false
        },
        "author": {
          "name": "author",
          "type": "varchar(80)",
          "primaryKey": false,
          "notNull": false,
          "autoincrement": false
        },
        "alias": {
          "name": "alias",
          "type": "varchar(20)",
          "primaryKey": false,
          "notNull": false,
          "autoincrement": false
        },
        "pdfOwnerId": {
          "name": "pdfOwnerId",
          "type": "bigint",
          "primaryKey": false,
          "notNull": false,
          "autoincrement": false
        }
      },
      "indexes": {},
      "foreignKeys": {
        "pdfs_pdfOwnerId_users_id_fk": {
          "name": "pdfs_pdfOwnerId_users_id_fk",
          "tableFrom": "pdfs",
          "tableTo": "users",
          "columnsFrom": [
            "pdfOwnerId"
          ],
          "columnsTo": [
            "id"
          ],
          "onDelete": "no action",
          "onUpdate": "no action"
        }
      },
      "compositePrimaryKeys": {
        "pdfs_id": {
          "name": "pdfs_id",
          "columns": [
            "id"
          ]
        }
      },
      "uniqueConstraints": {}
    },
    "users": {
      "name": "users",
      "columns": {
        "id": {
          "name": "id",
          "type": "serial",
          "primaryKey": false,
          "notNull": true,
          "autoincrement": true
        },
        "name": {
          "name": "name",
          "type": "varchar(30)",
          "primaryKey": false,
          "notNull": false,
          "autoincrement": false
        }
      },
      "indexes": {},
      "foreignKeys": {},
      "compositePrimaryKeys": {
        "users_id": {
          "name": "users_id",
          "columns": [
            "id"
          ]
        }
      },
      "uniqueConstraints": {}
    }
  },
  "schemas": {},
  "_meta": {
    "schemas": {},
    "tables": {},
    "columns": {}
  }
}